{
  "$schema": "https://mintlify.com/docs.json",
  "name": "BidAuc",
  "theme": "almond",
  "colors": {
    "primary": "#2563EB",
    "light": "#EFF6FF",
    "dark": "#1E3A5F"
  },
  "navbar": {
    "primary": {
      "type": "github",
      "href": "https://github.com/harshalw2003/BidAuc"
    }
  },
  "footer": {
    "socials": {
      "github": "https://github.com/harshalw2003/BidAuc"
    }
  },
  "navigation": {
    "tabs": [
      {
        "tab": "Documentation",
        "groups": [
          {
            "group": "Get Started",
            "pages": ["introduction", "quickstart", "architecture"]
          },
          {
            "group": "Core Concepts",
            "pages": ["concepts/roles", "concepts/jobs", "concepts/bidding"]
          },
          {
            "group": "Guides",
            "pages": ["guides/posting-a-job", "guides/placing-a-bid", "guides/managing-jobs", "guides/profile-setup"]
          }
        ]
      },
      {
        "tab": "API Reference",
        "groups": [
          {
            "group": "Authentication",
            "pages": ["api/auth/generate-otp", "api/auth/register", "api/auth/login", "api/auth/logout"]
          },
          {
            "group": "Users",
            "pages": ["api/users/get-profile", "api/users/update-details", "api/users/upload-picture", "api/users/get-providers"]
          },
          {
            "group": "Jobs",
            "pages": ["api/jobs/create", "api/jobs/list", "api/jobs/seeker-jobs", "api/jobs/provider-jobs"]
          },
          {
            "group": "Bids",
            "pages": ["api/bids/post", "api/bids/list", "api/bids/accept"]
          },
          {
            "group": "Categories",
            "pages": ["api/categories/list", "api/categories/get-one"]
          }
        ]
      }
    ]
  }
}
